resumable_upload/__init__.py
resumable_upload/exceptions.py
resumable_upload/fingerprint.py
resumable_upload/server.py
resumable_upload/storage.py
resumable_upload/url_storage.py
resumable_upload/client/__init__.py
resumable_upload/client/base.py
resumable_upload/client/retry.py
resumable_upload/client/stats.py
resumable_upload-0.0.1.dist-info/licenses/LICENSE
resumable_upload-0.0.1.dist-info/METADATA
resumable_upload-0.0.1.dist-info/WHEEL
resumable_upload-0.0.1.dist-info/top_level.txt
resumable_upload-0.0.1.dist-info/RECORD
