Metadata-Version: 2.4
Name: resumable-upload
Version: 0.0.1
Summary: A Python implementation of the `TUS resumable upload protocol` for server and client, with zero runtime dependencies.
Author-email: Injae Ryou <sts07142@naver.com>
License: MIT
Project-URL: Homepage, https://github.com/sts07142/resumable-upload
Project-URL: Documentation, https://github.com/sts07142/resumable-upload#readme
Project-URL: Repository, https://github.com/sts07142/resumable-upload
Project-URL: Issues, https://github.com/sts07142/resumable-upload/issues
Project-URL: Changelog, https://github.com/sts07142/resumable-upload/releases
Keywords: tus,upload,resumable,file-upload,server,client,http
Classifier: Development Status :: 4 - Beta
Classifier: Intended Audience :: Developers
Classifier: Topic :: Software Development :: Libraries :: Python Modules
Classifier: Topic :: Internet :: WWW/HTTP :: HTTP Servers
Classifier: Topic :: System :: Networking
Classifier: Programming Language :: Python :: 3
Classifier: Programming Language :: Python :: 3.9
Classifier: Programming Language :: Python :: 3.10
Classifier: Programming Language :: Python :: 3.11
Classifier: Programming Language :: Python :: 3.12
Classifier: Programming Language :: Python :: 3.13
Classifier: Programming Language :: Python :: 3.14
Classifier: Programming Language :: Python :: 3 :: Only
Requires-Python: >=3.9
License-File: LICENSE
Provides-Extra: dev
Requires-Dist: pytest>=7.0.0; extra == "dev"
Requires-Dist: pytest-cov>=4.0.0; extra == "dev"
Requires-Dist: ruff>=0.1.0; extra == "dev"
Requires-Dist: pre-commit>=3.0.0; extra == "dev"
Requires-Dist: tox>=4.0.0; extra == "dev"
Provides-Extra: test
Requires-Dist: pytest>=7.0.0; extra == "test"
Requires-Dist: pytest-cov>=4.0.0; extra == "test"
Requires-Dist: flask>=2.0.0; extra == "test"
Requires-Dist: fastapi>=0.100.0; extra == "test"
Requires-Dist: uvicorn>=0.38.0; extra == "test"
Requires-Dist: httpx>=0.24.0; extra == "test"
Requires-Dist: django>=3.2.0; extra == "test"
Dynamic: license-file
